xeosimplecalc/__init__.py
xeo_simple_calc-0.0.7.dist-info/LICENSE.txt
xeo_simple_calc-0.0.7.dist-info/METADATA
xeo_simple_calc-0.0.7.dist-info/WHEEL
xeo_simple_calc-0.0.7.dist-info/top_level.txt
xeo_simple_calc-0.0.7.dist-info/RECORD
