Metadata-Version: 2.1
Name: xeo-simple-calc
Version: 0.0.7
Summary: A small basic calculator
Home-page: https://github.com/XeoPlay/xeo-simple-calc
Author: XeoPlay
Author-email: xeoplay123456@gmail.com
License: UNKNOWN
Platform: UNKNOWN
Classifier: Programming Language :: Python :: 3
Classifier: License :: OSI Approved :: MIT License
Classifier: Operating System :: OS Independent
Requires-Python: >=3.6
